LICENSE
MANIFEST.in
README.md
setup.cfg
setup.py
booltest_rtt/__init__.py
booltest_rtt/database.py
booltest_rtt/errors.py
booltest_rtt/main.py
booltest_rtt/utils.py
booltest_rtt.egg-info/PKG-INFO
booltest_rtt.egg-info/SOURCES.txt
booltest_rtt.egg-info/dependency_links.txt
booltest_rtt.egg-info/entry_points.txt
booltest_rtt.egg-info/requires.txt
booltest_rtt.egg-info/top_level.txt